odoo10_addon_crm_location-10.0.1.0.0-py2.7-nspkg.pth
odoo/addons/crm_location/README.rst
odoo/addons/crm_location/__init__.py
odoo/addons/crm_location/__manifest__.py
odoo/addons/crm_location/i18n/bg.po
odoo/addons/crm_location/i18n/ca.po
odoo/addons/crm_location/i18n/de.po
odoo/addons/crm_location/i18n/es.po
odoo/addons/crm_location/i18n/es_ES.po
odoo/addons/crm_location/i18n/fi.po
odoo/addons/crm_location/i18n/fr.po
odoo/addons/crm_location/i18n/hr.po
odoo/addons/crm_location/i18n/it.po
odoo/addons/crm_location/i18n/pt_BR.po
odoo/addons/crm_location/i18n/sk.po
odoo/addons/crm_location/i18n/sl.po
odoo/addons/crm_location/i18n/tr_TR.po
odoo/addons/crm_location/i18n/zh_CN.po
odoo/addons/crm_location/models/__init__.py
odoo/addons/crm_location/models/crm_lead.py
odoo/addons/crm_location/static/description/icon.png
odoo/addons/crm_location/tests/__init__.py
odoo/addons/crm_location/tests/test_crm_location.py
odoo/addons/crm_location/views/crm_lead_view.xml
odoo10_addon_crm_location-10.0.1.0.0.dist-info/DESCRIPTION.rst
odoo10_addon_crm_location-10.0.1.0.0.dist-info/METADATA
odoo10_addon_crm_location-10.0.1.0.0.dist-info/RECORD
odoo10_addon_crm_location-10.0.1.0.0.dist-info/WHEEL
odoo10_addon_crm_location-10.0.1.0.0.dist-info/metadata.json
odoo10_addon_crm_location-10.0.1.0.0.dist-info/namespace_packages.txt
odoo10_addon_crm_location-10.0.1.0.0.dist-info/top_level.txt
